{
    "url": "https://www.saucedemo.com/",
    "suits": {
        "BATSuit": {
            "LoginModule": {
                "ValidLoginScenario": {
                    "step1": "Enter standard_user in Username",
                    "step2": "Enter secret_sauce in Password",
                    "step3": "Click Login button",
		    "step4": "Navigate to the Products page",
		    "step5": "Verify the Products title"
                }
            }
        },
        "RegressionSuit": {
            "LoginModule": {
                "ValidLoginScenario": {
                    "1": "Enter standard_user in Username",
                    "2": "Enter secret_sauce in Password",
                    "3": "Click Login button",
		    "4": "Navigate to the Products page",
		    "5": "Verify the Products title"
                },
                "InvalidUsernameScenario": {
                    "1": "Enter User in Username",
                    "2": "Enter secret_sauce in Password",
                    "3": "Click Login button",
		    "4": "Verify the 'Epic sadface: Username and password do not match any user in this service' error message"
                },
                "InvalidPasswordScenario": {
                    "1": "Enter standard_user in Username",
                    "2": "Enter secret in Password",
                    "3": "Click Login button",
	            "4": "Verify the 'Epic sadface: Username and password do not match any user in this service' error message"
                }
            },
            "ShoppingModule": {
                "AddToCartScenario": {
                    "1": "Enter standard_user in Username",
                    "2": "Enter secret_sauce in Password",
                    "3": "Click Login button",
		    "4": "Navigate to the Products page",
		    "5": "Click 'Add to cart' button",
		    "6": "Click 'shopping_cart_link'",
		    "7": "Verify 'Sauce Labs Backpack' item"
                },
                "ContinueShoppingScenario": {
                    "1": "Enter standard_user in Username",
                    "2": "Enter secret_sauce in Password",
                    "3": "Click Login button",
		    "4": "Navigate to the Products page",
		    "5": "Click 'Add to cart' button",
		    "6": "Click 'shopping_cart_link'",
		    "7": "Click 'Continue Shopping' button",
		    "8": "Verify the Products title"
                }
            }
        }
    }
}